gwproactor/__init__.py
gwproactor/app.py
gwproactor/callbacks.py
gwproactor/codecs.py
gwproactor/external_watchdog.py
gwproactor/io_loop.py
gwproactor/logger.py
gwproactor/logging_setup.py
gwproactor/message.py
gwproactor/proactor_implementation.py
gwproactor/proactor_interface.py
gwproactor/problems.py
gwproactor/py.typed
gwproactor/stats.py
gwproactor/str_tasks.py
gwproactor/sync_thread.py
gwproactor/watchdog.py
gwproactor/web_manager.py
gwproactor/actors/__init__.py
gwproactor/actors/actor.py
gwproactor/actors/rest.py
gwproactor/actors/web_event_listener.py
gwproactor/config/__init__.py
gwproactor/config/app_settings.py
gwproactor/config/links.py
gwproactor/config/logging.py
gwproactor/config/mqtt.py
gwproactor/config/paths.py
gwproactor/config/proactor_config.py
gwproactor/config/proactor_settings.py
gwproactor/links/__init__.py
gwproactor/links/acks.py
gwproactor/links/asyncio_timer_manager.py
gwproactor/links/link_manager.py
gwproactor/links/link_settings.py
gwproactor/links/link_state.py
gwproactor/links/message_times.py
gwproactor/links/mqtt.py
gwproactor/links/reuploads.py
gwproactor/links/timer_interface.py
gwproactor/persister/__init__.py
gwproactor/persister/exceptions.py
gwproactor/persister/interface.py
gwproactor/persister/simple_directory_writer.py
gwproactor/persister/stub.py
gwproactor/persister/timed_rolling_file.py
gwproactor_test/__init__.py
gwproactor_test/certs.py
gwproactor_test/clean.py
gwproactor_test/cli.py
gwproactor_test/event_consistency_checks.py
gwproactor_test/instrumented_links.py
gwproactor_test/instrumented_proactor.py
gwproactor_test/instrumented_stats.py
gwproactor_test/live_test_helper.py
gwproactor_test/logger_guard.py
gwproactor_test/persister_cli.py
gwproactor_test/py.typed
gwproactor_test/pytest_options.py
gwproactor_test/tree_live_test_helper.py
gwproactor_test/wait.py
gwproactor_test/config/dummy-hardware-layout.json
gwproactor_test/config/hardware-layout.json
gwproactor_test/dummies/__init__.py
gridworks_proactor-4.1.13.dist-info/METADATA
gridworks_proactor-4.1.13.dist-info/WHEEL
gridworks_proactor-4.1.13.dist-info/entry_points.txt
gridworks_proactor-4.1.13.dist-info/licenses/LICENSE
gridworks_proactor-4.1.13.dist-info/RECORD
