Metadata-Version: 2.4
Name: gridworks-proactor
Version: 4.1.13
Summary: Gridworks Proactor
Project-URL: Homepage, https://github.com/thegridelectric/gridworks-proactor
Project-URL: Repository, https://github.com/thegridelectric/gridworks-proactor
Project-URL: Documentation, https://gridworks-proactor.readthedocs.io
Project-URL: Changelog, https://github.com/thegridelectric/gridworks-proactor/releases
Author-email: Andrew Schweitzer <schweitz72@gmail.com>, Jessica Millar <jmillar@gridworks-consulting.com>
License-Expression: MIT
License-File: LICENSE
Classifier: Development Status :: 4 - Beta
Requires-Python: <4,>=3.11
Requires-Dist: aiohttp<4,>=3.11.11
Requires-Dist: gridworks-protocol<2,>=1.2.9
Requires-Dist: multidict<7,>=6.0.4
Requires-Dist: paho-mqtt<3,>=2.1.0
Requires-Dist: pydantic-settings<3,>=2.4.0
Requires-Dist: pydantic<3,>=2.10.0
Requires-Dist: python-dotenv<2,>=1.0.0
Requires-Dist: result<0.10,>=0.9.0
Requires-Dist: rich<15,>=14.0.0
Requires-Dist: xdg<7,>=6.0.0
Requires-Dist: yarl<2,>=1.9.2
Provides-Extra: tests
Requires-Dist: click<8.2.0; extra == 'tests'
Requires-Dist: freezegun<2,>=1.5.1; extra == 'tests'
Requires-Dist: gridworks-cert>=0.4.2; extra == 'tests'
Requires-Dist: pytest-asyncio>=0.20.3; extra == 'tests'
Requires-Dist: pytest>=7.2.0; extra == 'tests'
Requires-Dist: typer>=0.15.4; extra == 'tests'
